particlelife/__init__.py
particlelife/particle.py
particlelife/particle_life.py
particlelife-0.6.2.dist-info/METADATA
particlelife-0.6.2.dist-info/WHEEL
particlelife-0.6.2.dist-info/top_level.txt
particlelife-0.6.2.dist-info/RECORD
