Metadata-Version: 2.1
Name: particlelife
Version: 0.6.2
Author: MrPsyghost
Author-email: shivaypuri2000@gmail.com
Requires-Dist: pygame>=2.6.1
